hatchling_pyo3_plugin/__init__.py
hatchling_pyo3_plugin/hooks.py
hatchling_pyo3_plugin/py.typed
hatchling_pyo3_plugin-0.1.1.dist-info/METADATA
hatchling_pyo3_plugin-0.1.1.dist-info/WHEEL
hatchling_pyo3_plugin-0.1.1.dist-info/entry_points.txt
hatchling_pyo3_plugin-0.1.1.dist-info/licenses/LICENSE
hatchling_pyo3_plugin-0.1.1.dist-info/RECORD
