Metadata-Version: 2.4
Name: hatchling-pyo3-plugin
Version: 0.1.1
Summary: A Hatchling build hook plugin for building PyO3 Rust extensions
Project-URL: Documentation, https://frankie567.github.io/hatchling-pyo3-plugin/
Project-URL: Source, https://github.com/frankie567/hatchling-pyo3-plugin
Author-email: hatchling-pyo3-plugin <contact@francoisvoron.com>
License-File: LICENSE
Classifier: Programming Language :: Python :: 3 :: Only
Classifier: Programming Language :: Python :: 3.10
Requires-Python: >=3.10
Requires-Dist: hatchling>=1.15.1
